varpy/__init__.py
varpy/backtest/__init__.py
varpy/backtest/christophersen.py
varpy/backtest/model_backtest.py
varpy/data/__init__.py
varpy/data/SPX/SPX.csv.gz
varpy/data/SPX/__init__.py
varpy/models/__init__.py
varpy/models/base.py
varpy/models/evt.py
varpy/models/normal.py
varpy/models/student.py
varpy/regressions/__init__.py
varpy/regressions/arch.py
varpy/regressions/utils.py
varpy-2.0.1.dist-info/licenses/LICENSE
varpy-2.0.1.dist-info/METADATA
varpy-2.0.1.dist-info/WHEEL
varpy-2.0.1.dist-info/top_level.txt
varpy-2.0.1.dist-info/RECORD
