Metadata-Version: 2.4
Name: varpy
Version: 2.0.1
Summary: Value at Risk tools
Author-email: Elyes Mahjoubi <elyesmahjoubi@gmail.com>
Project-URL: repository, https://github.com/EM51641/varpy
Keywords: value at risk,risk management,financial risk,risk metrics
Classifier: Operating System :: OS Independent
Classifier: License :: OSI Approved :: MIT License
Requires-Python: >=3.10
License-File: LICENSE
Requires-Dist: pandas-stubs>=2.2.3.250308
Requires-Dist: pandas>=2.2.3
Requires-Dist: arch>=7.2.0
Requires-Dist: numpy>=2.2.5
Requires-Dist: scipy>=1.15.3
Requires-Dist: scipy-stubs>=1.15.3.0
Provides-Extra: dev
Requires-Dist: pytest>=7.0.0; extra == "dev"
Requires-Dist: pytest-cov>=4.0.0; extra == "dev"
Requires-Dist: mypy>=1.0.0; extra == "dev"
Requires-Dist: black>=23.0.0; extra == "dev"
Requires-Dist: isort>=5.0.0; extra == "dev"
Requires-Dist: flake8>=5.0.0; extra == "dev"
Dynamic: license-file
